{
	"embedded_geometry_info" : {
		"is_closed" : true,
		"volume" : 0.4087182068
	},
	"quadrature_info" : {
		"represented_volume" : 0.4087182068,
		"percentage_of_geometry_volume" : 100,
		"tot_num_points" : 279552,
		"num_of_points_per_full_element" : 64,
		"num_of_points_per_trimmed_element" : 64
	},
	"background_grid_info" : {
		"num_active_elements" : 4368,
		"num_trimmed_elements" : 2031,
		"num_full_elements" : 2337,
		"num_inactive_elements" : 98173
	},
	"elapsed_time_info" : {
		"total" : 2.2417413,
		"volume_time_info" : {
			"total" : 1.851587,
			"classification_of_elements" : 0.1492132,
			"computation_of_intersections" : 0.06175341667,
			"solution_of_moment_fitting_eqs" : 1.633093333,
			"construction_of_ggq_rules" : 0
		},
		"conditions_time_info" : {
			"total" : 0.0211217
		},
		"write_files_time_info" : {
			"total" : 0.3690326
		}
	},
	"conditions_infos_list" : [
		{
			"condition_id" : 1,
			"surf_area" : 0.200000003,
			"perc_surf_area_in_active_domain" : 100
		},
		{
			"condition_id" : 2,
			"surf_area" : 0.2000007629,
			"perc_surf_area_in_active_domain" : 100
		}
	]
}
